Workbook

Sheet Leia-me
A1: Comitê de orçamento — Real x Previsto
A3: Período: 03/08/2026 a 16/09/2026. Fonte do realizado: MotorCob (trilha, retornos dos fornecedores e parcelas do sistema de acordos).
A5: Como ler
A6: • Texto azul com fundo amarelo = premissa editável (aba Premissas e coluna 'Volume previsto'). Texto preto = fórmula.
A7: • Cada linha de 'Real x Previsto' é uma ação: régua do playbook x canal. O realizado de cada tentativa é atribuído à régua em que o cliente estava no dia (pela TAG).
A8: • Acordos são atribuídos à régua e ao canal do contato que os originou.
A9: • Recuperação prevista = acordos previstos x ticket médio x % de parcelas pagas. Receita = recuperação x % de remuneração (comissão/honorários).
A10: • Receita real projetada = valor acordado no período x % de parcelas pagas x % de remuneração (as parcelas futuras ainda não venceram).
A11: • ROI realizado (caixa) = recuperado até o fim do período x % de remuneração ÷ custo — cresce conforme as parcelas vencem.
A12: • Custo = custo variável das tentativas nos fornecedores. Custos fixos (operadores, licenças) não estão incluídos.
A13: • Decisão (critério do playbook): ROI ≥ 1,5x aprovação direta · 1,0x–1,5x aprova com plano · < 1,0x reprova ou exige justificativa.
A14: • 'Volume previsto' vem pré-preenchido com o volume realizado: assim o previsto mostra o que o benchmark esperava daquele volume. Para orçar o mês seguinte, substitua pelo volume planejado.
A16: Abas: Resumo · Premissas · Real x Previsto · KPIs safra-cluster · Migração de estados · Benchmarks (inclui sugestão de ordem de rotação — só muda por decisão do comitê).

Sheet Resumo
A1: Resumo do período
B3: Orçado (previsto) | C3: Custo real | D3: Receita prevista | E3: Receita real projetada | F3: Recuperado (caixa) | G3: ROI previsto | H3: ROI real | I3: Acordos previstos | J3: Acordos reais
A4: Voz | B4: =SUMIFS('Real x Previsto'!$G$4:$G$25,'Real x Previsto'!$C$4:$C$25,"Voz") | C4: =SUMIFS('Real x Previsto'!$U$4:$U$25,'Real x Previsto'!$C$4:$C$25,"Voz") | D4: =SUMIFS('Real x Previsto'!$P$4:$P$25,'Real x Previsto'!$C$4:$C$25,"Voz") | E4: =SUMIFS('Real x Previsto'!$AB$4:$AB$25,'Real x Previsto'!$C$4:$C$25,"Voz") | F4: =SUMIFS('Real x Previsto'!$Y$4:$Y$25,'Real x Previsto'!$C$4:$C$25,"Voz") | G4: =IF(B4>0,D4/B4,0) | H4: =IF(C4>0,E4/C4,0) | I4: =SUMIFS('Real x Previsto'!$K$4:$K$25,'Real x Previsto'!$C$4:$C$25,"Voz") | J4: =SUMIFS('Real x Previsto'!$W$4:$W$25,'Real x Previsto'!$C$4:$C$25,"Voz")
A5: Digital | B5: =SUMIFS('Real x Previsto'!$G$4:$G$25,'Real x Previsto'!$C$4:$C$25,"Digital") | C5: =SUMIFS('Real x Previsto'!$U$4:$U$25,'Real x Previsto'!$C$4:$C$25,"Digital") | D5: =SUMIFS('Real x Previsto'!$P$4:$P$25,'Real x Previsto'!$C$4:$C$25,"Digital") | E5: =SUMIFS('Real x Previsto'!$AB$4:$AB$25,'Real x Previsto'!$C$4:$C$25,"Digital") | F5: =SUMIFS('Real x Previsto'!$Y$4:$Y$25,'Real x Previsto'!$C$4:$C$25,"Digital") | G5: =IF(B5>0,D5/B5,0) | H5: =IF(C5>0,E5/C5,0) | I5: =SUMIFS('Real x Previsto'!$K$4:$K$25,'Real x Previsto'!$C$4:$C$25,"Digital") | J5: =SUMIFS('Real x Previsto'!$W$4:$W$25,'Real x Previsto'!$C$4:$C$25,"Digital")
A6: Total | B6: =SUM('Real x Previsto'!$G$4:$G$25) | C6: =SUM('Real x Previsto'!$U$4:$U$25) | D6: =SUM('Real x Previsto'!$P$4:$P$25) | E6: =SUM('Real x Previsto'!$AB$4:$AB$25) | F6: =SUM('Real x Previsto'!$Y$4:$Y$25) | G6: =IF(B6>0,D6/B6,0) | H6: =IF(C6>0,E6/C6,0) | I6: =SUM('Real x Previsto'!$K$4:$K$25) | J6: =SUM('Real x Previsto'!$W$4:$W$25)
A8: Decisão por ação (ROI previsto)
A9: Aprovação direta | B9: =COUNTIF('Real x Previsto'!$R$4:$R$25,"Aprovação direta")
A10: Aprova com plano | B10: =COUNTIF('Real x Previsto'!$R$4:$R$25,"Aprova com plano")
A11: Reprova ou justificar | B11: =COUNTIF('Real x Previsto'!$R$4:$R$25,"Reprova ou justificar")
A13: Custo = custo variável das tentativas nos fornecedores; custos fixos não estão incluídos, por isso o ROI por ação tende a ser alto. Receita = recuperação × % de remuneração.

Sheet Premissas
A1: Premissas
A3: Canal | B3: Código | C3: Taxa de contato prevista | D3: Custo unitário (R$)
A4: WhatsApp | B4: whatsapp | C4: 0.15 | D4: 0.3
A5: RCS | B5: rcs | C5: 0.07 | D5: 0.12
A6: Agente virtual | B6: agente_voz | C6: 0.03 | D6: 0.12
A7: Discador | B7: discador | C7: 0.03 | D7: 0.35
A8: SMS | B8: sms | C8: 0.015 | D8: 0.07
A9: E-mail | B9: email | C9: 0.015 | D9: 0.01
A11: % acordo sobre contato | C11: 0.25
A12: Ticket médio do acordo (R$) | C12: 3035.95
A13: % de parcelas pagas | C13: 0.8
A14: % de remuneração sobre o recuperado | C14: 0.15
A15: ROI para aprovação direta | C15: 1.5
A16: ROI mínimo (aprova com plano) | C16: 1

Sheet Real x Previsto
A1: Real x Previsto por ação (régua x canal)
E2: PREVISTO | T2: REAL (MotorCob)
A3: Régua | B3: Canal | C3: Vertical | D3: Fornecedor | E3: Volume previsto | F3: Custo unitário | G3: Orçado | H3: Taxa de contato prevista | I3: Contatos previstos | J3: % acordo s/ contato | K3: Acordos previstos | L3: Ticket médio | M3: % parcelas pagas | N3: Recuperação prevista | O3: % remuneração | P3: Receita prevista | Q3: ROI previsto | R3: Decisão | S3: Custo por acordo previsto | T3: Volume real | U3: Custo real | V3: Contatos reais | W3: Acordos reais | X3: Valor acordado | Y3: Recuperado (caixa) | Z3: Taxa de contato real | AA3: Recuperação real projetada | AB3: Receita real projetada | AC3: ROI real | AD3: ROI realizado (caixa) | AE3: Desvio de receita | AF3: Desvio de custo | AG3: Custo por acordo real
A4: Localização | B4: WhatsApp | C4: Digital | D4: sim | E4: 154 | F4: =IFERROR(INDEX(Premissas!$D$4:$D$9,MATCH($AH4,Premissas!$B$4:$B$9,0)),0) | G4: =E4*F4 | H4: =IFERROR(INDEX(Premissas!$C$4:$C$9,MATCH($AH4,Premissas!$B$4:$B$9,0)),0) | I4: =E4*H4 | J4: =Premissas!$C$11 | K4: =I4*J4 | L4: =Premissas!$C$12 | M4: =Premissas!$C$13 | N4: =K4*L4*M4 | O4: =Premissas!$C$14 | P4: =N4*O4 | Q4: =IF(G4>0,P4/G4,0) | R4: =IF(Q4>=Premissas!$C$15,"Aprovação direta",IF(Q4>=Premissas!$C$16,"Aprova com plano","Reprova ou justificar")) | S4: =IF(K4>0,G4/K4,0) | T4: 154 | U4: 46.2 | V4: 18 | W4: 2 | X4: 3381.74 | Y4: 535.03 | Z4: =IF(T4>0,V4/T4,0) | AA4: =X4*M4 | AB4: =AA4*O4 | AC4: =IF(U4>0,AB4/U4,0) | AD4: =IF(U4>0,Y4*O4/U4,0) | AE4: =IF(P4>0,AB4/P4-1,0) | AF4: =IF(G4>0,U4/G4-1,0) | AG4: =IF(W4>0,U4/W4,0) | AH4: whatsapp
A5: Localização | B5: RCS | C5: Digital | D5: sim | E5: 547 | F5: =IFERROR(INDEX(Premissas!$D$4:$D$9,MATCH($AH5,Premissas!$B$4:$B$9,0)),0) | G5: =E5*F5 | H5: =IFERROR(INDEX(Premissas!$C$4:$C$9,MATCH($AH5,Premissas!$B$4:$B$9,0)),0) | I5: =E5*H5 | J5: =Premissas!$C$11 | K5: =I5*J5 | L5: =Premissas!$C$12 | M5: =Premissas!$C$13 | N5: =K5*L5*M5 | O5: =Premissas!$C$14 | P5: =N5*O5 | Q5: =IF(G5>0,P5/G5,0) | R5: =IF(Q5>=Premissas!$C$15,"Aprovação direta",IF(Q5>=Premissas!$C$16,"Aprova com plano","Reprova ou justificar")) | S5: =IF(K5>0,G5/K5,0) | T5: 547 | U5: 65.64 | V5: 23 | W5: 10 | X5: 31427.37 | Y5: 25294.47 | Z5: =IF(T5>0,V5/T5,0) | AA5: =X5*M5 | AB5: =AA5*O5 | AC5: =IF(U5>0,AB5/U5,0) | AD5: =IF(U5>0,Y5*O5/U5,0) | AE5: =IF(P5>0,AB5/P5-1,0) | AF5: =IF(G5>0,U5/G5-1,0) | AG5: =IF(W5>0,U5/W5,0) | AH5: rcs
A6: Localização | B6: Agente virtual | C6: Voz | D6: sim | E6: 671 | F6: =IFERROR(INDEX(Premissas!$D$4:$D$9,MATCH($AH6,Premissas!$B$4:$B$9,0)),0) | G6: =E6*F6 | H6: =IFERROR(INDEX(Premissas!$C$4:$C$9,MATCH($AH6,Premissas!$B$4:$B$9,0)),0) | I6: =E6*H6 | J6: =Premissas!$C$11 | K6: =I6*J6 | L6: =Premissas!$C$12 | M6: =Premissas!$C$13 | N6: =K6*L6*M6 | O6: =Premissas!$C$14 | P6: =N6*O6 | Q6: =IF(G6>0,P6/G6,0) | R6: =IF(Q6>=Premissas!$C$15,"Aprovação direta",IF(Q6>=Premissas!$C$16,"Aprova com plano","Reprova ou justificar")) | S6: =IF(K6>0,G6/K6,0) | T6: 671 | U6: 80.52 | V6: 18 | W6: 1 | X6: 2302.1 | Y6: 230.21 | Z6: =IF(T6>0,V6/T6,0) | AA6: =X6*M6 | AB6: =AA6*O6 | AC6: =IF(U6>0,AB6/U6,0) | AD6: =IF(U6>0,Y6*O6/U6,0) | AE6: =IF(P6>0,AB6/P6-1,0) | AF6: =IF(G6>0,U6/G6-1,0) | AG6: =IF(W6>0,U6/W6,0) | AH6: agente_voz
A7: Localização | B7: Discador | C7: Voz | D7: sim | E7: 618 | F7: =IFERROR(INDEX(Premissas!$D$4:$D$9,MATCH($AH7,Premissas!$B$4:$B$9,0)),0) | G7: =E7*F7 | H7: =IFERROR(INDEX(Premissas!$C$4:$C$9,MATCH($AH7,Premissas!$B$4:$B$9,0)),0) | I7: =E7*H7 | J7: =Premissas!$C$11 | K7: =I7*J7 | L7: =Premissas!$C$12 | M7: =Premissas!$C$13 | N7: =K7*L7*M7 | O7: =Premissas!$C$14 | P7: =N7*O7 | Q7: =IF(G7>0,P7/G7,0) | R7: =IF(Q7>=Premissas!$C$15,"Aprovação direta",IF(Q7>=Premissas!$C$16,"Aprova com plano","Reprova ou justificar")) | S7: =IF(K7>0,G7/K7,0) | T7: 618 | U7: 216.3 | V7: 18 | W7: 4 | X7: 12591.69 | Y7: 8368.85 | Z7: =IF(T7>0,V7/T7,0) | AA7: =X7*M7 | AB7: =AA7*O7 | AC7: =IF(U7>0,AB7/U7,0) | AD7: =IF(U7>0,Y7*O7/U7,0) | AE7: =IF(P7>0,AB7/P7-1,0) | AF7: =IF(G7>0,U7/G7-1,0) | AG7: =IF(W7>0,U7/W7,0) | AH7: discador
A8: Localização | B8: SMS | C8: Digital | D8: sim | E8: 441 | F8: =IFERROR(INDEX(Premissas!$D$4:$D$9,MATCH($AH8,Premissas!$B$4:$B$9,0)),0) | G8: =E8*F8 | H8: =IFERROR(INDEX(Premissas!$C$4:$C$9,MATCH($AH8,Premissas!$B$4:$B$9,0)),0) | I8: =E8*H8 | J8: =Premissas!$C$11 | K8: =I8*J8 | L8: =Premissas!$C$12 | M8: =Premissas!$C$13 | N8: =K8*L8*M8 | O8: =Premissas!$C$14 | P8: =N8*O8 | Q8: =IF(G8>0,P8/G8,0) | R8: =IF(Q8>=Premissas!$C$15,"Aprovação direta",IF(Q8>=Premissas!$C$16,"Aprova com plano","Reprova ou justificar")) | S8: =IF(K8>0,G8/K8,0) | T8: 441 | U8: 30.87 | V8: 5 | W8: 2 | X8: 604.23 | Y8: 22.16 | Z8: =IF(T8>0,V8/T8,0) | AA8: =X8*M8 | AB8: =AA8*O8 | AC8: =IF(U8>0,AB8/U8,0) | AD8: =IF(U8>0,Y8*O8/U8,0) | AE8: =IF(P8>0,AB8/P8-1,0) | AF8: =IF(G8>0,U8/G8-1,0) | AG8: =IF(W8>0,U8/W8,0) | AH8: sms
A9: Localização | B9: E-mail | C9: Digital | D9: sim | E9: 256 | F9: =IFERROR(INDEX(Premissas!$D$4:$D$9,MATCH($AH9,Premissas!$B$4:$B$9,0)),0) | G9: =E9*F9 | H9: =IFERROR(INDEX(Premissas!$C$4:$C$9,MATCH($AH9,Premissas!$B$4:$B$9,0)),0) | I9: =E9*H9 | J9: =Premissas!$C$11 | K9: =I9*J9 | L9: =Premissas!$C$12 | M9: =Premissas!$C$13 | N9: =K9*L9*M9 | O9: =Premissas!$C$14 | P9: =N9*O9 | Q9: =IF(G9>0,P9/G9,0) | R9: =IF(Q9>=Premissas!$C$15,"Aprovação direta",IF(Q9>=Premissas!$C$16,"Aprova com plano","Reprova ou justificar")) | S9: =IF(K9>0,G9/K9,0) | T9: 256 | U9: 2.56 | V9: 4 | W9: 0 | X9: 0 | Y9: 0 | Z9: =IF(T9>0,V9/T9,0) | AA9: =X9*M9 | AB9: =AA9*O9 | AC9: =IF(U9>0,AB9/U9,0) | AD9: =IF(U9>0,Y9*O9/U9,0) | AE9: =IF(P9>0,AB9/P9-1,0) | AF9: =IF(G9>0,U9/G9-1,0) | AG9: =IF(W9>0,U9/W9,0) | AH9: email
A10: Giro (Não CPC) | B10: WhatsApp | C10: Digital | D10: sim | E10: 227 | F10: =IFERROR(INDEX(Premissas!$D$4:$D$9,MATCH($AH10,Premissas!$B$4:$B$9,0)),0) | G10: =E10*F10 | H10: =IFERROR(INDEX(Premissas!$C$4:$C$9,MATCH($AH10,Premissas!$B$4:$B$9,0)),0) | I10: =E10*H10 | J10: =Premissas!$C$11 | K10: =I10*J10 | L10: =Premissas!$C$12 | M10: =Premissas!$C$13 | N10: =K10*L10*M10 | O10: =Premissas!$C$14 | P10: =N10*O10 | Q10: =IF(G10>0,P10/G10,0) | R10: =IF(Q10>=Premissas!$C$15,"Aprovação direta",IF(Q10>=Premissas!$C$16,"Aprova com plano","Reprova ou justificar")) | S10: =IF(K10>0,G10/K10,0) | T10: 227 | U10: 68.1 | V10: 32 | W10: 6 | X10: 26468.63 | Y10: 14788.95 | Z10: =IF(T10>0,V10/T10,0) | AA10: =X10*M10 | AB10: =AA10*O10 | AC10: =IF(U10>0,AB10/U10,0) | AD10: =IF(U10>0,Y10*O10/U10,0) | AE10: =IF(P10>0,AB10/P10-1,0) | AF10: =IF(G10>0,U10/G10-1,0) | AG10: =IF(W10>0,U10/W10,0) | AH10: whatsapp
A11: Giro (Não CPC) | B11: RCS | C11: Digital | D11: sim | E11: 814 | F11: =IFERROR(INDEX(Premissas!$D$4:$D$9,MATCH($AH11,Premissas!$B$4:$B$9,0)),0) | G11: =E11*F11 | H11: =IFERROR(INDEX(Premissas!$C$4:$C$9,MATCH($AH11,Premissas!$B$4:$B$9,0)),0) | I11: =E11*H11 | J11: =Premissas!$C$11 | K11: =I11*J11 | L11: =Premissas!$C$12 | M11: =Premissas!$C$13 | N11: =K11*L11*M11 | O11: =Premissas!$C$14 | P11: =N11*O11 | Q11: =IF(G11>0,P11/G11,0) | R11: =IF(Q11>=Premissas!$C$15,"Aprovação direta",IF(Q11>=Premissas!$C$16,"Aprova com plano","Reprova ou justificar")) | S11: =IF(K11>0,G11/K11,0) | T11: 814 | U11: 97.68 | V11: 37 | W11: 6 | X11: 13354.04 | Y11: 503.58 | Z11: =IF(T11>0,V11/T11,0) | AA11: =X11*M11 | AB11: =AA11*O11 | AC11: =IF(U11>0,AB11/U11,0) | AD11: =IF(U11>0,Y11*O11/U11,0) | AE11: =IF(P11>0,AB11/P11-1,0) | AF11: =IF(G11>0,U11/G11-1,0) | AG11: =IF(W11>0,U11/W11,0) | AH11: rcs
A12: Giro (Não CPC) | B12: Agente virtual | C12: Voz | D12: sim | E12: 815 | F12: =IFERROR(INDEX(Premissas!$D$4:$D$9,MATCH($AH12,Premissas!$B$4:$B$9,0)),0) | G12: =E12*F12 | H12: =IFERROR(INDEX(Premissas!$C$4:$C$9,MATCH($AH12,Premissas!$B$4:$B$9,0)),0) | I12: =E12*H12 | J12: =Premissas!$C$11 | K12: =I12*J12 | L12: =Premissas!$C$12 | M12: =Premissas!$C$13 | N12: =K12*L12*M12 | O12: =Premissas!$C$14 | P12: =N12*O12 | Q12: =IF(G12>0,P12/G12,0) | R12: =IF(Q12>=Premissas!$C$15,"Aprovação direta",IF(Q12>=Premissas!$C$16,"Aprova com plano","Reprova ou justificar")) | S12: =IF(K12>0,G12/K12,0) | T12: 815 | U12: 97.8 | V12: 30 | W12: 10 | X12: 45869.05 | Y12: 5720.86 | Z12: =IF(T12>0,V12/T12,0) | AA12: =X12*M12 | AB12: =AA12*O12 | AC12: =IF(U12>0,AB12/U12,0) | AD12: =IF(U12>0,Y12*O12/U12,0) | AE12: =IF(P12>0,AB12/P12-1,0) | AF12: =IF(G12>0,U12/G12-1,0) | AG12: =IF(W12>0,U12/W12,0) | AH12: agente_voz
A13: Giro (Não CPC) | B13: Discador | C13: Voz | D13: sim | E13: 745 | F13: =IFERROR(INDEX(Premissas!$D$4:$D$9,MATCH($AH13,Premissas!$B$4:$B$9,0)),0) | G13: =E13*F13 | H13: =IFERROR(INDEX(Premissas!$C$4:$C$9,MATCH($AH13,Premissas!$B$4:$B$9,0)),0) | I13: =E13*H13 | J13: =Premissas!$C$11 | K13: =I13*J13 | L13: =Premissas!$C$12 | M13: =Premissas!$C$13 | N13: =K13*L13*M13 | O13: =Premissas!$C$14 | P13: =N13*O13 | Q13: =IF(G13>0,P13/G13,0) | R13: =IF(Q13>=Premissas!$C$15,"Aprovação direta",IF(Q13>=Premissas!$C$16,"Aprova com plano","Reprova ou justificar")) | S13: =IF(K13>0,G13/K13,0) | T13: 745 | U13: 260.75 | V13: 18 | W13: 7 | X13: 25030.45 | Y13: 20510.97 | Z13: =IF(T13>0,V13/T13,0) | AA13: =X13*M13 | AB13: =AA13*O13 | AC13: =IF(U13>0,AB13/U13,0) | AD13: =IF(U13>0,Y13*O13/U13,0) | AE13: =IF(P13>0,AB13/P13-1,0) | AF13: =IF(G13>0,U13/G13-1,0) | AG13: =IF(W13>0,U13/W13,0) | AH13: discador
A14: Giro (Não CPC) | B14: SMS | C14: Digital | D14: sim | E14: 604 | F14: =IFERROR(INDEX(Premissas!$D$4:$D$9,MATCH($AH14,Premissas!$B$4:$B$9,0)),0) | G14: =E14*F14 | H14: =IFERROR(INDEX(Premissas!$C$4:$C$9,MATCH($AH14,Premissas!$B$4:$B$9,0)),0) | I14: =E14*H14 | J14: =Premissas!$C$11 | K14: =I14*J14 | L14: =Premissas!$C$12 | M14: =Premissas!$C$13 | N14: =K14*L14*M14 | O14: =Premissas!$C$14 | P14: =N14*O14 | Q14: =IF(G14>0,P14/G14,0) | R14: =IF(Q14>=Premissas!$C$15,"Aprovação direta",IF(Q14>=Premissas!$C$16,"Aprova com plano","Reprova ou justificar")) | S14: =IF(K14>0,G14/K14,0) | T14: 604 | U14: 42.28 | V14: 10 | W14: 5 | X14: 12784.58 | Y14: 4022.43 | Z14: =IF(T14>0,V14/T14,0) | AA14: =X14*M14 | AB14: =AA14*O14 | AC14: =IF(U14>0,AB14/U14,0) | AD14: =IF(U14>0,Y14*O14/U14,0) | AE14: =IF(P14>0,AB14/P14-1,0) | AF14: =IF(G14>0,U14/G14-1,0) | AG14: =IF(W14>0,U14/W14,0) | AH14: sms
A15: Giro (Não CPC) | B15: E-mail | C15: Digital | D15: sim | E15: 236 | F15: =IFERROR(INDEX(Premissas!$D$4:$D$9,MATCH($AH15,Premissas!$B$4:$B$9,0)),0) | G15: =E15*F15 | H15: =IFERROR(INDEX(Premissas!$C$4:$C$9,MATCH($AH15,Premissas!$B$4:$B$9,0)),0) | I15: =E15*H15 | J15: =Premissas!$C$11 | K15: =I15*J15 | L15: =Premissas!$C$12 | M15: =Premissas!$C$13 | N15: =K15*L15*M15 | O15: =Premissas!$C$14 | P15: =N15*O15 | Q15: =IF(G15>0,P15/G15,0) | R15: =IF(Q15>=Premissas!$C$15,"Aprovação direta",IF(Q15>=Premissas!$C$16,"Aprova com plano","Reprova ou justificar")) | S15: =IF(K15>0,G15/K15,0) | T15: 236 | U15: 2.36 | V15: 5 | W15: 1 | X15: 522.81 | Y15: 174.27 | Z15: =IF(T15>0,V15/T15,0) | AA15: =X15*M15 | AB15: =AA15*O15 | AC15: =IF(U15>0,AB15/U15,0) | AD15: =IF(U15>0,Y15*O15/U15,0) | AE15: =IF(P15>0,AB15/P15-1,0) | AF15: =IF(G15>0,U15/G15-1,0) | AG15: =IF(W15>0,U15/W15,0) | AH15: email
... A25: Quebra | B25: Discador | C25: Voz | D25: sim | E25: 2 | F25: =IFERROR(INDEX(Premissas!$D$4:$D$9,MATCH($AH25,Premissas!$B$4:$B$9,0)),0) | G25: =E25*F25 | H25: =IFERROR(INDEX(Premissas!$C$4:$C$9,MATCH($AH25,Premissas!$B$4:$B$9,0)),0) | I25: =E25*H25 | J25: =Premissas!$C$11 | K25: =I25*J25 | L25: =Premissas!$C$12 | M25: =Premissas!$C$13 | N25: =K25*L25*M25 | O25: =Premissas!$C$14 | P25: =N25*O25 | Q25: =IF(G25>0,P25/G25,0) | R25: =IF(Q25>=Premissas!$C$15,"Aprovação direta",IF(Q25>=Premissas!$C$16,"Aprova com plano","Reprova ou justificar")) | S25: =IF(K25>0,G25/K25,0) | T25: 2 | U25: 0.7 | V25: 0 | W25: 0 | X25: 0 | Y25: 0 | Z25: =IF(T25>0,V25/T25,0) | AA25: =X25*M25 | AB25: =AA25*O25 | AC25: =IF(U25>0,AB25/U25,0) | AD25: =IF(U25>0,Y25*O25/U25,0) | AE25: =IF(P25>0,AB25/P25-1,0) | AF25: =IF(G25>0,U25/G25-1,0) | AG25: =IF(W25>0,U25/W25,0) | AH25: discador
A26: TOTAL | E26: =SUM(E4:E25) | G26: =SUM(G4:G25) | I26: =SUM(I4:I25) | K26: =SUM(K4:K25) | N26: =SUM(N4:N25) | P26: =SUM(P4:P25) | Q26: =IF(G26>0,P26/G26,0) | R26: =IF(Q26>=Premissas!$C$15,"Aprovação direta",IF(Q26>=Premissas!$C$16,"Aprova com plano","Reprova ou justificar")) | S26: =IF(K26>0,G26/K26,0) | T26: =SUM(T4:T25) | U26: =SUM(U4:U25) | V26: =SUM(V4:V25) | W26: =SUM(W4:W25) | X26: =SUM(X4:X25) | Y26: =SUM(Y4:Y25) | Z26: =IF(T26>0,V26/T26,0) | AA26: =SUM(AA4:AA25) | AB26: =SUM(AB4:AB25) | AC26: =IF(U26>0,AB26/U26,0) | AD26: =IF(U26>0,Y26*Premissas!$C$14/U26,0) | AE26: =IF(P26>0,AB26/P26-1,0) | AF26: =IF(G26>0,U26/G26-1,0) | AG26: =IF(W26>0,U26/W26,0)

Sheet KPIs safra-cluster
A1: KPIs por safra e cluster (frentes do playbook)
A3: safra | B3: cluster | C3: clientes | D3: % base qualificada | E3: localizados | F3: % localizados | G3: % loc WA | H3: % loc RC | I3: % loc AV | J3: % loc DC | K3: % loc SM | L3: % loc EM | M3: custo localizacao | N3: custo por cpc descoberto | O3: ncp para cpa | P3: cpb recuperados | Q3: tentativas ate contato | R3: acordos | S3: % acordo sobre cpc voz | T3: % acordo sobre retorno digital | U3: custo total | V3: custo por acordo | W3: % parcelas em dia | X3: % acordos quitados | Y3: quebras | Z3: % regularizacao ate d5 | AA3: % retorna estoque
A4: 2026-08 | B4: A1 | C4: 46 | D4: 0.9783 | E4: 29 | F4: 0.6304 | G4: 0.1522 | H4: 0.1304 | I4: 0.1522 | J4: 0.087 | K4: 0.0435 | L4: 0.0652 | M4: 125.13 | N4: 4.31 | O4: 20 | P4: 9 | Q4: 7 | R4: 13 | S4: 0.375 | T4: 0.3182 | U4: 171.58 | V4: 13.2 | W4: 1 | X4: 1 | Y4: 0
A5: 2026-08 | B5: A2 | C5: 24 | D5: 1 | E5: 12 | F5: 0.5 | G5: 0.125 | H5: 0.2083 | I5: 0.0833 | J5: 0 | K5: 0 | L5: 0.0833 | M5: 63.25 | N5: 5.27 | O5: 9 | P5: 3 | Q5: 7.8 | R5: 8 | S5: 0.4 | T5: 0.6 | U5: 80.89 | V5: 10.11 | W5: 0.75 | X5: 1 | Y5: 1 | AA5: 0
A6: 2026-08 | B6: A3 | C6: 23 | D6: 1 | E6: 11 | F6: 0.4783 | G6: 0.1304 | H6: 0.1304 | I6: 0.1304 | J6: 0.0435 | K6: 0.0435 | L6: 0 | M6: 70.92 | N6: 6.45 | O6: 8 | P6: 6 | Q6: 6.6 | R6: 5 | S6: 0.375 | T6: 0.2222 | U6: 85.01 | V6: 17 | W6: 1 | X6: 1 | Y6: 0
A7: 2026-08 | B7: B1 | C7: 67 | D7: 0.9701 | E7: 36 | F7: 0.5373 | G7: 0.1493 | H7: 0.1194 | I7: 0.0896 | J7: 0.1194 | K7: 0.0448 | L7: 0.0149 | M7: 190.91 | N7: 5.3 | O7: 22 | P7: 15 | Q7: 7.9 | R7: 20 | S7: 0.2778 | T7: 0.4545 | U7: 241.76 | V7: 12.09 | W7: 0.9091 | X7: 1 | Y7: 1 | Z7: 0 | AA7: 1
A8: 2026-08 | B8: B2 | C8: 29 | D8: 1 | E8: 18 | F8: 0.6207 | G8: 0.1379 | H8: 0.1379 | I8: 0.1034 | J8: 0.1034 | K8: 0.1034 | L8: 0.0345 | M8: 80.26 | N8: 4.46 | O8: 10 | P8: 10 | Q8: 5.9 | R8: 8 | S8: 0.125 | T8: 0.35 | U8: 119.23 | V8: 14.9 | W8: 1 | X8: 1 | Y8: 0
A9: 2026-08 | B9: B3 | C9: 35 | D9: 1 | E9: 16 | F9: 0.4571 | G9: 0.1714 | H9: 0.1714 | I9: 0 | J9: 0 | K9: 0.0857 | L9: 0.0286 | M9: 37.8 | N9: 2.36 | O9: 13 | P9: 3 | Q9: 5 | R9: 9 | T9: 0.4737 | U9: 47.88 | V9: 5.32 | W9: 1 | Y9: 0
A10: 2026-08 | B10: M1 | C10: 69 | D10: 0.9565 | E10: 40 | F10: 0.5797 | G10: 0.1739 | H10: 0.1449 | I10: 0.1594 | J10: 0.087 | K10: 0.0145 | L10: 0 | M10: 189.5 | N10: 4.74 | O10: 22 | P10: 29 | Q10: 6.2 | R10: 19 | S10: 0.3077 | T10: 0.2558 | U10: 271.51 | V10: 14.29 | W10: 1 | X10: 1 | Y10: 0
A11: 2026-08 | B11: M2 | C11: 51 | D11: 0.9608 | E11: 27 | F11: 0.5294 | G11: 0.0588 | H11: 0.1373 | I11: 0.1176 | J11: 0.1961 | K11: 0.0196 | L11: 0 | M11: 127.32 | N11: 4.72 | O11: 15 | P11: 17 | Q11: 6.6 | R11: 13 | S11: 0.2174 | T11: 0.381 | U11: 178.16 | V11: 13.7 | W11: 1 | X11: 1 | Y11: 0
A12: 2026-08 | B12: M3 | C12: 42 | D12: 1 | E12: 24 | F12: 0.5714 | G12: 0.0476 | H12: 0.1905 | I12: 0.2381 | J12: 0.0952 | K12: 0 | L12: 0 | M12: 102.21 | N12: 4.26 | O12: 11 | P12: 14 | Q12: 5.3 | R12: 9 | S12: 0.2609 | T12: 0.2 | U12: 163.36 | V12: 18.15 | W12: 1 | X12: 1 | Y12: 0
A13: 2026-09 | B13: A1 | C13: 3 | D13: 1 | E13: 0 | F13: 0 | G13: 0 | H13: 0 | I13: 0 | J13: 0 | K13: 0 | L13: 0 | M13: 7.9 | O13: 0 | P13: 0 | R13: 0 | U13: 7.9 | Y13: 0
A14: 2026-09 | B14: B1 | C14: 4 | D14: 1 | E14: 0 | F14: 0 | G14: 0 | H14: 0 | I14: 0 | J14: 0 | K14: 0 | L14: 0 | M14: 8.07 | O14: 0 | P14: 0 | R14: 0 | U14: 8.07 | Y14: 0
A15: 2026-09 | B15: B2 | C15: 1 | D15: 1 | E15: 1 | F15: 1 | G15: 0 | H15: 1 | I15: 0 | J15: 0 | K15: 0 | L15: 0 | M15: 0.12 | N15: 0.12 | O15: 0 | P15: 0 | Q15: 1 | R15: 1 | T15: 1 | U15: 0.36 | V15: 0.36 | Y15: 0
A16: 2026-09 | B16: B3 | C16: 1 | D16: 1 | E16: 0 | F16: 0 | G16: 0 | H16: 0 | I16: 0 | J16: 0 | K16: 0 | L16: 0 | M16: 1.06 | O16: 0 | P16: 0 | R16: 0 | U16: 1.06 | Y16: 0
A17: 2026-09 | B17: M1 | C17: 2 | D17: 1 | E17: 1 | F17: 0.5 | G17: 0 | H17: 0 | I17: 0 | J17: 0 | K17: 0.5 | L17: 0 | M17: 4.13 | N17: 4.13 | O17: 1 | P17: 0 | Q17: 9 | R17: 0 | T17: 0 | U17: 4.13 | Y17: 0
A18: 2026-09 | B18: M3 | C18: 3 | D18: 1 | E18: 2 | F18: 0.6667 | G18: 0 | H18: 0.6667 | I18: 0 | J18: 0 | K18: 0 | L18: 0 | M18: 2.48 | N18: 1.24 | O18: 0 | P18: 0 | Q18: 1 | R18: 1 | T18: 0.5 | U18: 5.14 | V18: 5.14 | W18: 1 | X18: 1 | Y18: 0
A19: TOTAL | C19: 400 | D19: 0.98 | E19: 217 | F19: 0.5425 | G19: 0.125 | H19: 0.15 | I19: 0.12 | J19: 0.09 | K19: 0.0375 | L19: 0.02 | M19: 1011.06 | N19: 4.66 | O19: 131 | P19: 106 | Q19: 6.5 | R19: 106 | S19: 0.2835 | T19: 0.3571 | U19: 1386.04 | V19: 13.08 | W19: 0.9714 | X19: 1 | Y19: 2 | Z19: 0 | AA19: 0.5

Sheet Migração de estados
A1: Migração de estados no período (de → para)
A3: de \ para | B3: LOC | C3: CPA | D3: CPB | E3: NCP | F3: PRE | G3: COL | H3: QBR | I3: LIQ | J3: BLQ | K3: Total
A4: ENTRADA | B4: 400 | C4: 0 | D4: 0 | E4: 0 | F4: 0 | G4: 0 | H4: 0 | I4: 0 | J4: 0 | K4: =SUM(B4:J4)
A5: LOC | B5: 0 | C5: 86 | D5: 0 | E5: 310 | F5: 0 | G5: 0 | H5: 0 | I5: 0 | J5: 4 | K5: =SUM(B5:J5)
A6: CPA | B6: 0 | C6: 0 | D6: 203 | E6: 0 | F6: 0 | G6: 106 | H6: 0 | I6: 0 | J6: 0 | K6: =SUM(B6:J6)
A7: CPB | B7: 0 | C7: 106 | D7: 0 | E7: 5 | F7: 0 | G7: 0 | H7: 0 | I7: 0 | J7: 0 | K7: =SUM(B7:J7)
A8: NCP | B8: 0 | C8: 131 | D8: 0 | E8: 0 | F8: 0 | G8: 0 | H8: 0 | I8: 0 | J8: 0 | K8: =SUM(B8:J8)
A9: PRE | B9: 0 | C9: 0 | D9: 0 | E9: 0 | F9: 0 | G9: 42 | H9: 2 | I9: 12 | J9: 0 | K9: =SUM(B9:J9)
A10: COL | B10: 0 | C10: 0 | D10: 0 | E10: 0 | F10: 65 | G10: 0 | H10: 0 | I10: 4 | J10: 0 | K10: =SUM(B10:J10)
A11: QBR | B11: 0 | C11: 1 | D11: 0 | E11: 0 | F11: 0 | G11: 0 | H11: 0 | I11: 0 | J11: 0 | K11: =SUM(B11:J11)
A12: LIQ | B12: 0 | C12: 0 | D12: 0 | E12: 0 | F12: 0 | G12: 0 | H12: 0 | I12: 0 | J12: 0 | K12: =SUM(B12:J12)
A13: BLQ | B13: 0 | C13: 0 | D13: 0 | E13: 0 | F13: 0 | G13: 0 | H13: 0 | I13: 0 | J13: 0 | K13: =SUM(B13:J13)

Sheet Benchmarks
A1: Benchmarks observados (recalibram as premissas do mês seguinte)
A3: Régua | B3: Canal | C3: Tentativas | D3: Contatos | E3: Custo | F3: Taxa de contato | G3: Custo por contato | H3: % acordo s/ contato
A4: Localização | B4: WhatsApp | C4: 154 | D4: 18 | E4: 46.2 | F4: 0.1169 | G4: 2.57 | H4: 0.1111
A5: Localização | B5: RCS | C5: 547 | D5: 23 | E5: 65.64 | F5: 0.042 | G5: 2.85 | H5: 0.4348
A6: Localização | B6: Agente virtual | C6: 671 | D6: 18 | E6: 80.52 | F6: 0.0268 | G6: 4.47 | H6: 0.0556
A7: Localização | B7: Discador | C7: 618 | D7: 18 | E7: 216.3 | F7: 0.0291 | G7: 12.02 | H7: 0.2222
A8: Localização | B8: SMS | C8: 441 | D8: 5 | E8: 30.87 | F8: 0.0113 | G8: 6.17 | H8: 0.4
A9: Localização | B9: E-mail | C9: 256 | D9: 4 | E9: 2.56 | F9: 0.0156 | G9: 0.64 | H9: 0
A10: Giro (Não CPC) | B10: WhatsApp | C10: 227 | D10: 32 | E10: 68.1 | F10: 0.141 | G10: 2.13 | H10: 0.1875
A11: Giro (Não CPC) | B11: RCS | C11: 814 | D11: 37 | E11: 97.68 | F11: 0.0455 | G11: 2.64 | H11: 0.1622
A12: Giro (Não CPC) | B12: Agente virtual | C12: 815 | D12: 30 | E12: 97.8 | F12: 0.0368 | G12: 3.26 | H12: 0.3333
A13: Giro (Não CPC) | B13: Discador | C13: 745 | D13: 18 | E13: 260.75 | F13: 0.0242 | G13: 14.49 | H13: 0.3889
A14: Giro (Não CPC) | B14: SMS | C14: 604 | D14: 10 | E14: 42.28 | F14: 0.0166 | G14: 4.23 | H14: 0.5
A15: Giro (Não CPC) | B15: E-mail | C15: 236 | D15: 5 | E15: 2.36 | F15: 0.0212 | G15: 0.47 | H15: 0.2
... A23: Preventivo / colchão | B23: RCS | C23: 51 | D23: 9 | E23: 6.12 | F23: 0.1765 | G23: 0.68 | H23: 0
A24: Preventivo / colchão | B24: Discador | C24: 2 | D24: 0 | E24: 0.7 | F24: 0
A25: Quebra | B25: Discador | C25: 2 | D25: 0 | E25: 0.7 | F25: 0
A27: Sugestão de ordem de rotação (menor custo por contato nas réguas massivas)
A28: Sugestão para o comitê: a ordem vigente em regras/regua.json só muda por decisão do comitê.
A29: Posição sugerida | B29: Canal | C29: Posição atual | D29: Tentativas | E29: Contatos | F29: Taxa de contato | G29: Custo por contato
A30: 1 | B30: WhatsApp | C30: 1 | D30: 586 | E30: 111 | F30: 0.1894 | G30: 1.58
A31: 2 | B31: RCS | C31: 2 | D31: 1566 | E31: 96 | F31: 0.0613 | G31: 1.96
A32: 3 | B32: Agente virtual | C32: 3 | D32: 1851 | E32: 74 | F32: 0.04 | G32: 3
A33: 4 | B33: SMS | C33: 5 | D33: 1217 | E33: 20 | F33: 0.0164 | G33: 4.26
A34: 5 | B34: Discador | C34: 4 | D34: 1986 | E34: 62 | F34: 0.0312 | G34: 11.21
